fastapi_permissions_alive/__init__.py
fastapi_permissions_alive/example.py
fastapi_permissions_alive-1.0.2.dist-info/WHEEL
fastapi_permissions_alive-1.0.2.dist-info/METADATA
fastapi_permissions_alive-1.0.2.dist-info/RECORD
