Metadata-Version: 2.1
Name: fastapi_permissions_alive
Version: 1.0.2
Summary: Row Level Permissions for FastAPI
Home-page: https://github.com/FabianRutten/fastapi-permissions-alive
Author: Fabian Rutten
Author-email: fabianrutten@gmail.com
Requires-Python: >=3.6
Classifier: Development Status :: 4 - Beta
Classifier: Intended Audience :: Developers
Classifier: License :: Freely Distributable
Classifier: Programming Language :: Python :: 3.7
Classifier: Programming Language :: Python :: 3.8
Classifier: Programming Language :: Python :: 3 :: Only
Classifier: Topic :: Internet :: WWW/HTTP :: HTTP Servers
Requires-Dist: fastapi >= 0.33.0
Requires-Dist: python-multipart >= 0.0.5
Requires-Dist: black ; extra == "dev"
Requires-Dist: flake8 ; extra == "dev"
Requires-Dist: flake8-comprehensions ; extra == "dev"
Requires-Dist: isort >= 5.0.0 ; extra == "dev"
Requires-Dist: keyring ; extra == "dev"
Requires-Dist: pre-commit ; extra == "dev"
Requires-Dist: pyjwt ; extra == "dev"
Requires-Dist: passlib[bcrypt] ; extra == "dev"
Requires-Dist: fastapi[all] ; extra == "dev"
Requires-Dist: pytest >= 4.0.0 ; extra == "test"
Requires-Dist: pytest-cov ; extra == "test"
Requires-Dist: pytest-mock ; extra == "test"
Requires-Dist: pytest-asyncio ; extra == "test"
Requires-Dist: pytest-randomly ; extra == "test"
Requires-Dist: tox ; extra == "test"
Provides-Extra: dev
Provides-Extra: test
